{   
    "actual" : {
        "title" : "Actueel",
        "events" : {
        "title" : "Om te noteren",
        "cards" : [
            {
                "date" : "14 mei 2022",
                "description" : "Studiedag"
            },
            {
                "date" : "27 april t/m 12 mei 2022",
                "description" : "Meivakantie"
            },
            {
                "date" : "24 mei t/m 2 juni 2022",
                "description" : "Toetsweken"
            },
            {
                "date" : "15 juni 2022",
                "description" : "Studiedag"
            }]
        },
        "posts" : {
            "title" : "Nieuws",
            "cards" : [
            {
                "title" : "BREAKING",
                "description" : "De Meerpaal tijdelijk niet telefonisch bereikbaar",
                "date" : "2 uur geleden"
            },
            {
                "title" : "NIEUWS",
                "description" : "De Meerpaal bestaat 40 jaar en dat mag gevierd worden!",
                "date" : "6 dagen geleden"
            },
            {
                "title" : "LEERLINGVERHALEN",
                "description" : "De eerste schooldag van Joanne was even wennen",
                "date" : "15 juni 2022"
            }]
        } 
    },

    "guide" : {
        "title" : "Ahoy Meerpaler!",
        "description" : "Op zoek naar informatie over vakanties, verlof of de leerlingenraad? Download de schoolgids of ga naar de pagina Mijn school.",
        "pinkButton" : "Download de schoolgids",
        "blueButton" : "Mijn school →"
    },

    "footer":   {
        "credits" : {
            "copyright" : "©2022 Calvijn", 
            "privacy" : "Privacyverklaring", 
            "design" : "Ontwerp Doordacht"
        },
        "contact" : {
            "title" : "Contact",
            "adres" : "Kreeftstraat",
            "postalcode" :  "44 3067 JV Rotterdam",
            "openinghours" : "Op schooldagen open van 08.00 tot 16.30 uur",
            "phone" : "010 286 1313", 
            "mail" : "info@vmbo-demeerpaal.nl"
        },
        "sitemap": {
            "title": "Sitemap",
            "links": {
                "Welkom" : "Welkom",
                "Ik ben nieuw" : "Ik ben nieuw",
                "Mijn school" : "Mijn school",
                "Voor ouders" : "Voor ouders",
                "Organisatie" : "Organisatie",
                "Nieuws" : "Nieuws",
                "Agenda" : "Agenda",
                "Vacatures" : "Vacatures",
                "Contact" : "Contact",
                "Portaal↗" : "Portaal↗",
                "Comenius↗" : "Comenius↗"
            }
        }
    }
}
